{"fields": ["DocCount", "DocArticleUuid", "DocDoi", "TreatId", "TreatGenusEpithet", "TreatSpeciesEpithet", "TreatAuthority"],
"labels": {
"DocCount": "Number of Articles",
"DocArticleUuid": "Article UUID",
"DocDoi": "Article DOI",
"TreatId": "Treatment UUID",
"TreatGenusEpithet": "Taxon Genus",
"TreatSpeciesEpithet": "Taxon Species",
"TreatAuthority": "Taxon Autority"
},
"data": [
{
"DocCount": "1",
"DocArticleUuid": "FFEDFFC4FFDFFFE2FFF0FFFDFFACFFD7",
"DocDoi": "http://dx.doi.org/10.3897/zookeys.822.30880",
"TreatId": "410342EDEDA74FFD71A533CEBE469C59",
"TreatGenusEpithet": "Ceratophysella",
"TreatSpeciesEpithet": "denticulata",
"TreatAuthority": "Bagnall, 1941"
},
{
"DocCount": "1",
"DocArticleUuid": "FFEDFFC4FFDFFFE2FFF0FFFDFFACFFD7",
"DocDoi": "http://dx.doi.org/10.3897/zookeys.822.30880",
"TreatId": "6F8FFAA04E18636CB421FCA45ECF5B12",
"TreatGenusEpithet": "Ceratophysella",
"TreatSpeciesEpithet": "communis",
"TreatAuthority": "Folsom, 1898"
},
{
"DocCount": "1",
"DocArticleUuid": "FFEDFFC4FFDFFFE2FFF0FFFDFFACFFD7",
"DocDoi": "http://dx.doi.org/10.3897/zookeys.822.30880",
"TreatId": "C9D7B5A3B6663848A5EC5E3E133E78AE",
"TreatGenusEpithet": "Ceratophysella",
"TreatSpeciesEpithet": "liguladorsi",
"TreatAuthority": "Lee, 1974"
},
{
"DocCount": "1",
"DocArticleUuid": "FFEDFFC4FFDFFFE2FFF0FFFDFFACFFD7",
"DocDoi": "http://dx.doi.org/10.3897/zookeys.822.30880",
"TreatId": "50498604A36F60A8888D285031149530",
"TreatGenusEpithet": "Ceratophysella",
"TreatSpeciesEpithet": "skarzynskii",
"TreatAuthority": "Weiner & Sun"
}
]
}